{
	"class" : {
		"title:text:" : "vitor 5/16/2016 16:49",
		"title:text:category:" : "vitor 5/16/2016 16:50",
		"unclassifiedTag" : "vitor 5/16/2016 16:25" },
	"instance" : {
		"beVisible" : "vitor 5/16/2016 13:59",
		"category" : "vitor 5/16/2016 13:58",
		"category:" : "vitor 5/16/2016 13:58",
		"date" : "vitor 5/16/2016 13:58",
		"date:" : "vitor 5/16/2016 13:58",
		"initialize" : "vitor 8/3/2016 17:51",
		"isUnclassified" : "vitor 5/16/2016 16:53",
		"isVisible" : "vitor 5/16/2016 13:59",
		"notVisible" : "vitor 5/16/2016 13:59",
		"text" : "vitor 5/16/2016 13:58",
		"text:" : "vitor 5/16/2016 13:58",
		"title" : "vitor 5/16/2016 13:58",
		"title:" : "vitor 5/16/2016 13:58",
		"visible" : "vitor 5/16/2016 13:58",
		"visible:" : "vitor 5/16/2016 13:58" } }
